{
    "name": "E2-Listening",
    "types": "video",
    "note": "",
    "videoArray": [
        {
            "link": "",
            "questions": [
                {
                    "question": "In a typical week, the speaker says that her time usually revolves around",
                    "options": [
                      "~Seeing test subjects",
                      "=Publishing papers",
                      "~Fluctuating baselines",
                      "~None of the above"
                    ],
                    "id": "101",
                    "answer": "",
                    "practicelinks": []
                },
                {
                    "question": "When the glass is described as ‘half-full’ it is called the",
                    "options": [
                      "=Gain frame",
                      "~Loss frame",
                      "~Boost frame",
                      "~Blow frame"
                    ],
                    "id": "102",
                    "answer": "",
                    "practicelinks": []
                },
                {
                    "question": "Once the ‘loss frame’ gets into an individual’s mind-set, it",
                    "options": [
                      "~Lets go immediately",
                      "~Takes a while to let go",
                      "=Sticks",
                      "~None of these"
                    ],
                    "id": "103",
                    "answer": "",
                    "practicelinks": []
                },
                {
                    "question": "The two experiments were conducted to confirm or refute the hypothesis that",
                    "options": [
                      "~It is easier to convert from gain frame to loss frame",
                      "=It is easier to convert from loss frame to gain frame",
                      "=It is not easy to convert either way",
                      "=None of the above"
                    ],
                    "id": "104",
                    "answer": "",
                    "practicelinks": []
                },
                {
                    "question": "Conversion from ‘loss to gain’ takes longer because",
                    "options": [
                      "~The mind resists the attempt to change from loss to gain",
                      "~Of a fundamental tendency to tilt towards the negative",
                      "~It is easier to shift from gain to loss than the other way round",
                      "=All of the above"
                    ],
                    "id": "105",
                    "answer": "",
                    "practicelinks": []
                },
                {
                    "question": "The speaker says that to her, personally, all this research means",
                    "options": [
                      "~It takes work and effort to see the up-side",
                      "~It takes practice to see the up-side",
                      "~You can train your mind to see the up-side",
                      "=All of the above"
                    ],
                    "id": "106",
                    "answer": "",
                    "practicelinks": []
                },
                {
                    "question": "Writing for a few minutes each day about things you’re grateful for can dramatically",
                    "options": [
                      "=Boost happiness, wellbeing and health",
                      "~Reduce happiness, wellbeing and health",
                      "~Stabilize happiness, wellbeing and health",
                      "~All of the above"
                    ],
                    "id": "107",
                    "answer": "",
                    "practicelinks": []
                }
            ]
        }
    ]
}
